funer/__init__.py
funer/aggregators/__init__.py
funer/aggregators/majority_voting_aggregators.py
funer/annotators/__init__.py
funer/annotators/base_annotator.py
funer/annotators/dictionary_annotator.py
funer/annotators/span_condition_annotator.py
funer/annotators/token_condition_annotator.py
funer/converters/__init__.py
funer/converters/sequence_label_to_sequence_label.py
funer/converters/sequence_label_to_span_labels_converter.py
funer/converters/span_labels_to_sequence_label_converter.py
funer/converters/utils.py
funer/document.py
funer/entity_span.py
funer/labeling_function_applier.py
funer/utils.py
funer-0.0.2.dist-info/WHEEL
funer-0.0.2.dist-info/METADATA
funer-0.0.2.dist-info/RECORD
