Metadata-Version: 2.1
Name: funer
Version: 0.0.2
Summary: Rule based Named Entity Recognition tool.
License: MIT
Author: Koga Kobayashi
Author-email: kajyuuen@gmail.com
Requires-Python: >=3.7,<4.0
Classifier: License :: OSI Approved :: MIT License
Classifier: Programming Language :: Python :: 3
Classifier: Programming Language :: Python :: 3.10
Classifier: Programming Language :: Python :: 3.7
Classifier: Programming Language :: Python :: 3.8
Classifier: Programming Language :: Python :: 3.9
Requires-Dist: CJKwrap (>=2.2,<3.0)
Requires-Dist: pyahocorasick (>=1.4.4,<2.0.0)
Requires-Dist: spacy (>=3.2.4,<4.0.0)
Requires-Dist: texttable (>=1.6.4,<2.0.0)
Requires-Dist: wcwidth (>=0.2.5,<0.3.0)
